ra_crypto/__init__.py
ra_crypto/aes/__init__.py
ra_crypto/aes/core.py
ra_crypto/ibe/__init__.py
ra_crypto/ibe/ibe_rsa.py
ra_crypto-1.0.2.dist-info/DESCRIPTION.rst
ra_crypto-1.0.2.dist-info/METADATA
ra_crypto-1.0.2.dist-info/RECORD
ra_crypto-1.0.2.dist-info/WHEEL
ra_crypto-1.0.2.dist-info/metadata.json
ra_crypto-1.0.2.dist-info/top_level.txt
